lribeiro.cherrypy.test-1.1.0-py3.4-nspkg.pth
lribeiro/cherrypy/test/__init__.py
lribeiro/cherrypy/test/test_case.py
lribeiro/cherrypy/test/base_test_case.py
lribeiro/cherrypy/test/httpstatus.py
lribeiro.cherrypy.test-1.1.0.dist-info/WHEEL
lribeiro.cherrypy.test-1.1.0.dist-info/top_level.txt
lribeiro.cherrypy.test-1.1.0.dist-info/DESCRIPTION.rst
lribeiro.cherrypy.test-1.1.0.dist-info/namespace_packages.txt
lribeiro.cherrypy.test-1.1.0.dist-info/METADATA
lribeiro.cherrypy.test-1.1.0.dist-info/metadata.json
lribeiro.cherrypy.test-1.1.0.dist-info/RECORD
