Metadata-Version: 2.0
Name: lribeiro.cherrypy.test
Version: 1.1.0
Summary: Test utilities for CherryPy
Home-page: http://bitbucket.org/livioribeiro/cherrypy-test
Author: Livio Ribeiro
Author-email: livioribeiro@outlook.com
License: BSD License
Keywords: cherrypy,test,unittest,py.test,nosetests
Platform: UNKNOWN
Classifier: Development Status :: 4 - Beta
Classifier: Environment :: Web Environment
Classifier: Framework :: CherryPy
Classifier: Intended Audience :: Developers
Classifier: License :: OSI Approved :: BSD License
Classifier: Operating System :: OS Independent
Classifier: Programming Language :: Python
Classifier: Programming Language :: Python :: 2
Classifier: Programming Language :: Python :: 2.7
Classifier: Programming Language :: Python :: 3
Classifier: Programming Language :: Python :: Implementation :: PyPy
Classifier: Topic :: Internet :: WWW/HTTP
Classifier: Topic :: Internet :: WWW/HTTP :: Dynamic Content
Classifier: Topic :: Software Development :: Testing
Requires-Dist: CherryPy
